scr/__init__.py
scr/api_tools.py
scr/azure_tools.py
scr/fabric_tools.py
scr/large_language_tools.py
msq_data_store_tools-1.1.0.dist-info/METADATA
msq_data_store_tools-1.1.0.dist-info/WHEEL
msq_data_store_tools-1.1.0.dist-info/top_level.txt
msq_data_store_tools-1.1.0.dist-info/RECORD
