Metadata-Version: 2.4
Name: msq_data_store_tools
Version: 1.1.0
Summary: This is a utility package designed to enable the data team to integrate with the MSQ data lake, i.e. the DataStore
Home-page: https://github.com/freemavens/data_store_tools
Author: Damian Rumble <damian.rumble@forge.com>
Dynamic: author
Dynamic: description
Dynamic: description-content-type
Dynamic: home-page
Dynamic: summary
